monashspa/__init__.py
monashspa/__version__.py
monashspa/PHS1011/__init__.py
monashspa/PHS2061/PHS2061_Q3_Fourier_Analysis.ipynb
monashspa/PHS2061/PHS2061_Q3_Fourier_Analysis.py
monashspa/PHS2061/PHS2061_Q3_Guitar_Pluck.wav
monashspa/PHS2061/PHS2061_Q3_Synthesiser.ipynb
monashspa/PHS2061/PHS2061_Q3_Synthesiser.py
monashspa/PHS2061/PHS20x1UncertaintiesData.csv
monashspa/PHS2061/__init__.py
monashspa/PHS2061/fitting_tutorial.py
monashspa/PHS2062/PHS2062_chisquare_illustration.py
monashspa/PHS2062/PHS2062_data_creation.py
monashspa/PHS2062/PHS2062_gas_data.csv
monashspa/PHS2062/PHS2062_gas_fit.ipynb
monashspa/PHS2062/PHS2062_gas_fit.py
monashspa/PHS2062/PHS2062_gas_short_2_data.csv
monashspa/PHS2062/PHS2062_gas_short_data.csv
monashspa/PHS2062/PHS2062_pendulum_fit.py
monashspa/PHS2062/__init__.py
monashspa/PHS2081/__init__.py
monashspa/PHS3000/PET.py
monashspa/PHS3000/__init__.py
monashspa/PHS3000/betaray.py
monashspa/PHS3000/holes_in_ge.py
monashspa/PHS3000/microwave_transmission.py
monashspa/PHS3000/mossbauer.py
monashspa/PHS3000/muon.py
monashspa/PHS3000/optical_tweezers.py
monashspa/PHS3000/reflex_klystron.py
monashspa/PHS3000/resistivity_germanium.py
monashspa/PHS3000/rubidium_spectroscopy.py
monashspa/PHS3000/thermoelectricity.py
monashspa/PHS3000/tutorials/PHS3000UncertaintiesData.csv
monashspa/PHS3000/tutorials/__init__.py
monashspa/PHS3000/tutorials/fitting.py
monashspa/PHS3302/__init__.py
monashspa/PHS3302/calorimeter/__init__.py
monashspa/PHS3302/calorimeter/calorimeter.ipynb
monashspa/PHS3302/calorimeter/calorimeter.py
monashspa/PHS3302/calorimeter/model/__init__.py
monashspa/PHS3302/calorimeter/model/calorimeter.py
monashspa/PHS3302/calorimeter/model/layer.py
monashspa/PHS3302/calorimeter/model/particle.py
monashspa/PHS3302/calorimeter/model/simulation.py
monashspa/PHS3302/d0_lifetime/__init__.py
monashspa/PHS3302/d0_lifetime/d0_lifetime.ipynb
monashspa/PHS3302/d0_lifetime/d0_lifetime.py
monashspa/common/__init__.py
monashspa/common/admca.py
monashspa-1.10.0.dist-info/licenses/COPYING
monashspa-1.10.0.dist-info/METADATA
monashspa-1.10.0.dist-info/WHEEL
monashspa-1.10.0.dist-info/top_level.txt
monashspa-1.10.0.dist-info/RECORD
